README.rst
setup.py
sc2bank/__init__.py
sc2bank/__main__.py
sc2bank/cli.py
sc2bank/gui.py
sc2bank/sc2bank.py
sc2bank.egg-info/PKG-INFO
sc2bank.egg-info/SOURCES.txt
sc2bank.egg-info/dependency_links.txt
sc2bank.egg-info/top_level.txt
sc2bank/test/__init__.py
sc2bank/test/test_sc2bank.py