Metadata-Version: 1.1
Name: sc2bank
Version: 0.3
Summary: Validate SC2Bank XML document signatures.
Home-page: https://github.com/winny-/sc2bank
Author: Winston Weinert
Author-email: sc2bank@fastmail.fm
License: MIT / BSD 3-clause
Platform: UNKNOWN
Classifier: License :: OSI Approved :: BSD License
Classifier: License :: OSI Approved :: MIT License
Classifier: Natural Language :: English
Classifier: Operating System :: OS Independent
Classifier: Programming Language :: Python :: 2.7
Classifier: Programming Language :: Python :: 3
Classifier: Topic :: Utilities
Classifier: Intended Audience :: End Users/Desktop
Classifier: Environment :: X11 Applications :: Qt
Classifier: Environment :: Console
Classifier: Development Status :: 4 - Beta
